{
  "Guy": {
    "FLUX-32": [
      "c-2026-05-06t12-05-00-000z"
    ],
    "FLUX-117": [
      "c-flux117-groom"
    ],
    "FLUX-94": [
      "c-flux94-groom"
    ],
    "FLUX-127": [
      "c-flux127-groom"
    ],
    "FLUX-97": [
      "c-flux97-groom",
      "c-2026-05-08t04-00-08-078z"
    ],
    "FLUX-72": [
      "c-flux72-groom"
    ],
    "FLUX-79": [
      "c-2026-05-07t06-55-00-000z-flux-79"
    ],
    "FLUX-80": [
      "c-2026-05-07t06-55-00-000z-flux-80"
    ],
    "FLUX-65": [
      "c-1778131426196-flux-65.md",
      "c-2026-05-07t05-57-49-673z"
    ],
    "FLUX-33": [
      "c-2026-05-06t12-06-00-000z",
      "c-2026-05-07t13-01-33-5429940-10-00-flux-33",
      "c-2026-05-07t03-58-47-248z",
      "c-2026-05-07t03-53-39-4816199z-flux-33"
    ],
    "FLUX-18": [
      "c-2026-05-06t07-33-00-000z",
      "c-2026-05-06t07-37-17-476z",
      "c-2026-05-07t03-53-39-4816199z-flux-18"
    ],
    "FLUX-38": [
      "c-2026-05-06t12-41-00-000z",
      "c-2026-05-07t13-01-33-5429940-10-00-flux-38",
      "c-2026-05-07t03-53-26-951z",
      "c-2026-05-07t03-53-39-4816199z-flux-38"
    ],
    "FLUX-40": [
      "c-2026-05-06t12-43-00-000z",
      "c-2026-05-07t03-53-39-4816199z-flux-40",
      "c-2026-05-07t03-53-39-4816199z-flux-40-todo"
    ],
    "FLUX-42": [
      "c-2026-05-07t13-01-33-5429940-10-00-flux-42",
      "c-2026-05-07t03-15-44-640z",
      "c-2026-05-07t03-53-39-4816199z-flux-42"
    ],
    "FLUX-56": [
      "c-2026-05-07t03-53-39-4816199z-flux-56"
    ],
    "FLUX-58": [
      "c-2026-05-07t03-53-39-4816199z-flux-58"
    ],
    "FLUX-6": [
      "c-2026-05-06t06-56-11-085z",
      "c-2026-05-06t07-29-00-000z",
      "c-2026-05-06t07-34-26-739z",
      "c-2026-05-06t12-40-00-000z"
    ],
    "FLUX-36": [
      "c-2026-05-06t12-09-00-000z"
    ],
    "FLUX-35": [
      "c-2026-05-06t12-08-00-000z"
    ],
    "FLUX-34": [
      "c-2026-05-06t12-07-00-000z"
    ],
    "FLUX-119": [
      "c-flux119-plan"
    ],
    "FLUX-115": [
      "c-flux115-plan",
      "c-flux115-done"
    ],
    "FLUX-116": [
      "c-flux116-plan",
      "c-flux116-done"
    ],
    "FLUX-124": [
      "c-flux124-groom",
      "c-2026-05-08t07-34-34-488z",
      "c-flux124-done",
      "c-2026-05-08t07-49-16-607z",
      "c-flux124-fixes"
    ],
    "FLUX-121": [
      "c-2026-05-08-plan",
      "c-2026-05-08-done",
      "c-2026-05-08t06-53-34-411z",
      "c-2026-05-08-docs-scope",
      "c-flux121-done"
    ],
    "FLUX-122": [
      "c-2026-05-08-plan",
      "c-2026-05-08-done",
      "c-flux122-done"
    ],
    "FLUX-73": [
      "c-2026-05-07t06-50-00-000z-flux-73",
      "c-flux73-ready",
      "c-flux73-done"
    ],
    "FLUX-75": [
      "c-2026-05-07t06-50-00-000z-flux-75",
      "c-flux75-ready",
      "c-flux75-done"
    ],
    "FLUX-76": [
      "c-2026-05-07t06-55-00-000z-flux-76",
      "c-flux76-ready",
      "c-flux76-done"
    ],
    "FLUX-77": [
      "c-2026-05-07t06-55-00-000z-flux-77",
      "c-flux77-ready",
      "c-flux77-done"
    ],
    "FLUX-78": [
      "c-2026-05-07t06-55-00-000z-flux-78",
      "c-flux78-ready",
      "c-flux78-done"
    ],
    "FLUX-93": [
      "c-flux93-groom",
      "c-flux93-plan",
      "c-flux93-impl",
      "c-2026-05-08t03-47-16-638z",
      "c-flux93-revision",
      "c-flux93-v3",
      "c-flux93-read-state",
      "c-flux93-close"
    ],
    "FLUX-107": [
      "c-flux107-groom",
      "c-flux107-impl",
      "c-flux107-close"
    ],
    "FLUX-111": [
      "c-flux111-groom",
      "c-flux111-done"
    ],
    "FLUX-114": [
      "c-flux114-groom",
      "c-flux114-impl",
      "c-flux114-close"
    ],
    "FLUX-110": [
      "c-flux110-done"
    ],
    "FLUX-106": [
      "c-2026-05-07t23-59-12-032z",
      "c-flux106-groom",
      "c-flux106-summary",
      "c-2026-05-08t00-19-31-327z",
      "c-flux106-v2",
      "c-2026-05-08t00-22-50-913z",
      "c-flux106-v3",
      "c-2026-05-08t00-24-29-159z",
      "c-flux106-v4",
      "c-2026-05-08t00-29-26-642z",
      "c-flux106-close"
    ],
    "FLUX-109": [
      "c-flux109-groom",
      "c-flux109-done",
      "c-flux109-fix",
      "c-flux109-close"
    ],
    "FLUX-74": [
      "c-2026-05-07t06-50-00-000z-flux-74",
      "c-flux74-plan",
      "c-flux74-done",
      "c-flux74-close"
    ],
    "FLUX-99": [
      "c-2026-05-08t12-00-00-000z",
      "c-2026-05-07t15-19-33-872z"
    ],
    "FLUX-102": [
      "c-2026-05-07t15-33-52-101z",
      "c-2026-05-07t15-33-58-895z",
      "c-2026-05-07t15-34-05-509z",
      "c-2026-05-08t12-00-00-000z"
    ],
    "FLUX-89": [
      "c-2026-05-08t10-00-00-000z",
      "c-2026-05-08t10-05-00-000z"
    ],
    "FLUX-88": [
      "c-2026-05-07t12-21-00-000z",
      "c-2026-05-07t12-25-00-000z",
      "c-2026-05-08t10-00-00-000z"
    ],
    "FLUX-104": [
      "c-2026-05-08t02-10-00",
      "c-2026-05-08t02-00-00",
      "c-2026-05-08t01-00-00",
      "c-2026-05-07t15-37-10-311z"
    ],
    "FLUX-95": [
      "c-2026-05-08t00-02-00-000z",
      "c-2026-05-08t00-15-00-000z"
    ],
    "FLUX-100": [
      "c-agent-grooming",
      "c-agent-implementation",
      "c-agent-completion"
    ],
    "FLUX-98": [
      "c-agent-grooming",
      "c-agent-implementation",
      "c-agent-implementation-sticky"
    ],
    "FLUX-50": [
      "c-2026-05-07t13-01-33-5429940-10-00-flux-50",
      "c-2026-05-07t03-07-37-337z",
      "c-2026-05-07t03-53-39-4816199z-flux-50",
      "c-2026-05-07t14-00-00-000z",
      "c-2026-05-07t14-15-00-000z"
    ],
    "FLUX-128": [
      "c-2026-05-08t08-25-04-512z",
      "c-2026-05-08t08-23-00-000z"
    ],
    "FLUX-126": [
      "c-flux126-plan"
    ]
  }
}